bonn-1.0.7.dist-info/METADATA
bonn-1.0.7.dist-info/WHEEL
bonn-1.0.7.dist-info/license_files/LICENSE.md
bonn/__init__.py
bonn/utils.py
bonn/taxonomy.py
bonn/settings.py
bonn/extract.py
bonn/category_manager.py
bonn/_bonn.cpython-310-darwin.so
bonn-1.0.7.dist-info/RECORD
