Metadata-Version: 2.1
Name: bonn
Version: 1.0.7
Classifier: Programming Language :: Rust
Classifier: Programming Language :: Python :: Implementation :: CPython
Classifier: Programming Language :: Python :: Implementation :: PyPy
Requires-Dist: nltk ~=3.7
Requires-Dist: sortedcontainers ~=2.4.0
Requires-Dist: elasticsearch
Requires-Dist: elasticsearch-dsl ~=7.0
Requires-Dist: numpy
Requires-Dist: finalfusion
Requires-Dist: dynaconf
License-File: LICENSE.md
Summary: Created for ONS. Proof-of-concept mmap'd Rust word2vec implementation linked with category matching
Keywords: nlp,search
Author-email: Chris Nixon <chris.nixon@flaxandteal.co.uk>, Phil Weir <phil.weir@flaxandteal.co.uk>
License: MIT
Requires-Python: >=3.8
Project-URL: Source Code, https://github.com/flaxandteal/bonn-py
